{
  "action": {
    "description": "Read third time as amended in the Senate \u2013 PASSED - 24-10-1AYES \u2013 Adams, Anthon, Bernt, Bjerke, Blaylock, Burtenshaw, Carlson, Cook, Den Hartog, Foreman, Galloway, Grow, Guthrie, Harris, Lakey, Lenney, Lent, Nichols, Okuniewicz, Ricks, Shippy, Toews, VanOrden, WoodwardNAYS \u2013 Hart, Kohl, Ruchti, Semmelroth, Taylor, Ward-Engelking, Wintrow, Woller(Rabe), Zito, ZuiderveldAbsent and excused \u2013 KeyserFloor Sponsor - LakeyTitle apvd - to House",
    "date": "2025-03-26",
    "organization_id": "~{\"classification\": \"upper\"}",
    "classification": [],
    "related_entities": []
  },
  "bill_id": "H 0271"
}