{
  "legislative_session": "2025",
  "identifier": "S 1131",
  "title": "APPROPRIATIONS \u2013 DEPARTMENT OF INSURANCE \u2013 Relates to the appropriation to the to the Department of Insurance for fiscal year 2026.",
  "from_organization": "~{\"classification\": \"upper\"}",
  "classification": [
    "bill"
  ],
  "subject": [
    "APPROPRIATIONS",
    "INSURANCE"
  ],
  "abstracts": [],
  "other_titles": [
    {
      "note": "short title",
      "title": "Approp, dept of insurance, add\u2019l"
    }
  ],
  "other_identifiers": [],
  "actions": [
    {
      "description": "Introduced; read first time; referred to JR for Printing",
      "date": "2025-02-25",
      "organization_id": "~{\"classification\": \"upper\"}",
      "classification": [
        "introduction"
      ],
      "related_entities": []
    },
    {
      "description": "Reported Printed; referred to Finance",
      "date": "2025-02-26",
      "organization_id": "~{\"classification\": \"upper\"}",
      "classification": [],
      "related_entities": []
    },
    {
      "description": "Reported out of Committee with Do Pass Recommendation; Filed for second reading",
      "date": "2025-02-26",
      "organization_id": "~{\"classification\": \"upper\"}",
      "classification": [
        "committee-passage-favorable"
      ],
      "related_entities": []
    },
    {
      "description": "Read second time; filed for Third Reading",
      "date": "2025-02-27",
      "organization_id": "~{\"classification\": \"upper\"}",
      "classification": [
        "reading-2"
      ],
      "related_entities": []
    },
    {
      "description": "Retained on calendar",
      "date": "2025-02-28",
      "organization_id": "~{\"classification\": \"upper\"}",
      "classification": [],
      "related_entities": []
    },
    {
      "description": "Retained on calendar",
      "date": "2025-03-03",
      "organization_id": "~{\"classification\": \"upper\"}",
      "classification": [],
      "related_entities": []
    },
    {
      "description": "Read third time in full \u2013 PASSED - 23-11-1AYES \u2013 Adams, Bernt, Blaylock, Burtenshaw, Carlson, Cook, Den Hartog, Galloway, Grow, Guthrie, Harris, Hart, Lakey, Lent, Mathews(Rabe), Ricks, Ruchti, Semmelroth, Taylor, VanOrden, Ward-Engelking, Wintrow, WoodwardNAYS \u2013 Bjerke, Foreman, Keyser, Kohl, Lenney, Nichols, Okuniewicz, Shippy, Toews, Zito, ZuiderveldAbsent and excused \u2013 AnthonFloor Sponsor - HartTitle apvd - to House",
      "date": "2025-03-04",
      "organization_id": "~{\"classification\": \"upper\"}",
      "classification": [
        "passage"
      ],
      "related_entities": []
    },
    {
      "description": "Received from the Senate, Filed for First Reading",
      "date": "2025-03-05",
      "organization_id": "~{\"classification\": \"lower\"}",
      "classification": [],
      "related_entities": []
    },
    {
      "description": "Read First Time, Filed for Second Reading",
      "date": "2025-03-05",
      "organization_id": "~{\"classification\": \"lower\"}",
      "classification": [
        "reading-1"
      ],
      "related_entities": []
    },
    {
      "description": "Read second time; Filed for Third Reading",
      "date": "2025-03-06",
      "organization_id": "~{\"classification\": \"lower\"}",
      "classification": [
        "reading-2"
      ],
      "related_entities": []
    },
    {
      "description": "U.C. to hold place on third reading calendar until Monday, March 10, 2025",
      "date": "2025-03-07",
      "organization_id": "~{\"classification\": \"lower\"}",
      "classification": [],
      "related_entities": []
    },
    {
      "description": "U.C. to hold place on third reading calendar one legislative day",
      "date": "2025-03-10",
      "organization_id": "~{\"classification\": \"lower\"}",
      "classification": [],
      "related_entities": []
    },
    {
      "description": "Read Third Time in Full \u2013 PASSED - 35-33-2AYES \u2013 Achilles, Andrus, Barbieri, Berch, Cannon, Cheatum, Church, Clow, Cornilles, Dygert, Egbert, Erickson, Fuhriman, Furniss, Galaviz, Gannon, Handy, Healey, Horman, Manwaring, McCann, Mickelsen, Miller, Nelsen, Petzke, Pickett, Pohanka, Raybould, Raymond, Rubel, Sauter, Tanner(14), Vander Woude, Weber, WheelerNAYS \u2013 Alfieri, Beiswenger, Boyle, Bruce, Burgoyne, Cayler, Crane(12), Crane(13), Ehardt, Ehlers, Garner, Harris, Hawkins, Hill, Holtzclaw, Hostetler, Leavitt, Marmon, Mendive, Mitchell, Monks, Palmer, Price, Rasor, Redman, Scott, Shepherd, Shirts, Skaug, Tanner(13), Thompson, Wisniewski, Mr. SpeakerAbsent \u2013 Green, MathiasFloor Sponsor - FurnissTitle apvd - to Senate",
      "date": "2025-03-11",
      "organization_id": "~{\"classification\": \"lower\"}",
      "classification": [
        "passage",
        "reading-3"
      ],
      "related_entities": []
    },
    {
      "description": "Returned From House Passed; referred to enrolling",
      "date": "2025-03-12",
      "organization_id": "~{\"classification\": \"upper\"}",
      "classification": [
        "enrolled"
      ],
      "related_entities": []
    },
    {
      "description": "Reported enrolled; signed by President; to House for signature of Speaker",
      "date": "2025-03-12",
      "organization_id": "~{\"classification\": \"upper\"}",
      "classification": [],
      "related_entities": []
    },
    {
      "description": "Received from Senate; Signed by Speaker; Returned to Senate",
      "date": "2025-03-13",
      "organization_id": "~{\"classification\": \"lower\"}",
      "classification": [
        "passage"
      ],
      "related_entities": []
    },
    {
      "description": "Reported signed by the Speaker & ordered delivered to Governor",
      "date": "2025-03-13",
      "organization_id": "~{\"classification\": \"upper\"}",
      "classification": [
        "executive-receipt"
      ],
      "related_entities": []
    },
    {
      "description": "Reported delivered to Governor at 3:55 p.m. on 03/13/25",
      "date": "2025-03-14",
      "organization_id": "~{\"classification\": \"upper\"}",
      "classification": [
        "executive-receipt"
      ],
      "related_entities": []
    },
    {
      "description": "Signed by Governor on 03/19/25    Session Law Chapter 134    Effective: 07/01/2025",
      "date": "2025-03-20",
      "organization_id": "~{\"classification\": \"upper\"}",
      "classification": [
        "executive-signature"
      ],
      "related_entities": []
    }
  ],
  "sponsorships": [
    {
      "name": "FINANCE COMMITTEE",
      "classification": "primary",
      "entity_type": "organization",
      "primary": true,
      "person_id": null,
      "organization_id": "~{\"chamber\": \"upper\", \"name\": \"FINANCE COMMITTEE\"}"
    }
  ],
  "related_bills": [],
  "versions": [
    {
      "note": "Bill Text",
      "links": [
        {
          "url": "https://legislature.idaho.gov/wp-content/uploads/sessioninfo/2025/legislation/S1131.pdf",
          "media_type": "application/pdf"
        }
      ],
      "date": "",
      "classification": ""
    }
  ],
  "documents": [
    {
      "note": "Statement of Purpose / Fiscal Note",
      "links": [
        {
          "url": "https://legislature.idaho.gov/wp-content/uploads/sessioninfo/2025/legislation/S1131SOP.pdf",
          "media_type": "application/pdf"
        }
      ],
      "date": "",
      "classification": ""
    },
    {
      "note": "Legislative Co-sponsors",
      "links": [
        {
          "url": "https://legislature.idaho.gov/wp-content/uploads/sessioninfo/2025/legislation/S1131LegCo.pdf",
          "media_type": "application/pdf"
        }
      ],
      "date": "",
      "classification": ""
    }
  ],
  "citations": [
    {
      "publication": "Idaho Session Laws 2025",
      "citation": "Chapter 134",
      "citation_type": "chapter",
      "effective": "2025-07-01",
      "expires": null,
      "url": null
    }
  ],
  "sources": [
    {
      "url": "https://legislature.idaho.gov/sessioninfo/2025/legislation/S1131/",
      "note": ""
    }
  ],
  "extras": {},
  "jurisdiction": {
    "id": "ocd-jurisdiction/country:us/state:id/government",
    "name": "Idaho",
    "classification": "state",
    "division_id": "ocd-division/country:us/state:id"
  },
  "scraped_at": "2025-07-25T05:48:20+00:00",
  "_id": "f878bc34-691a-11f0-87a6-0ecd267b5f67"
}