{"legislative_session": "2025", "identifier": "SR 107", "title": "PRAYER RESOLUTION \u2013 States findings of the Senate and supports observing an official time of prayer each day of the regular session of the Idaho Legislature.", "from_organization": "~{\"classification\": \"upper\"}", "classification": ["resolution"], "subject": ["LEGISLATURE", "RELIGION AND CHURCHES", "RESOLUTIONS"], "abstracts": [], "other_titles": [{"note": "short title", "title": "Prayer, support"}], "other_identifiers": [], "actions": [{"description": "Introduced; read first time; referred to JR for Printing", "date": "2025-02-19", "organization_id": "~{\"classification\": \"upper\"}", "classification": ["introduction"], "related_entities": []}, {"description": "Reported Printed; referred to 10th order; held one legislative day", "date": "2025-02-20", "organization_id": "~{\"classification\": \"upper\"}", "classification": [], "related_entities": []}, {"description": "Retained on calendar", "date": "2025-03-07", "organization_id": "~{\"classification\": \"upper\"}", "classification": [], "related_entities": []}, {"description": "Read in full \u2013 ADOPTED \u2013 voice voteFloor Sponsor \u2013 ToewsTitle apvd \u2013 Filed in Office of Secretary of Senate", "date": "2025-03-12", "organization_id": "~{\"classification\": \"upper\"}", "classification": ["passage", "reading-3"], "related_entities": []}], "sponsorships": [{"name": "STATE AFFAIRS COMMITTEE", "classification": "primary", "entity_type": "organization", "primary": true, "person_id": null, "organization_id": "~{\"chamber\": \"upper\", \"name\": \"STATE AFFAIRS COMMITTEE\"}"}], "related_bills": [], "versions": [{"note": "Bill Text", "links": [{"url": "https://legislature.idaho.gov/wp-content/uploads/sessioninfo/2025/legislation/SR107.pdf", "media_type": "application/pdf"}], "date": "", "classification": ""}], "documents": [{"note": "Statement of Purpose / Fiscal Note", "links": [{"url": "https://legislature.idaho.gov/wp-content/uploads/sessioninfo/2025/legislation/SR107SOP.pdf", "media_type": "application/pdf"}], "date": "", "classification": ""}], "citations": [], "sources": [{"url": "https://legislature.idaho.gov/sessioninfo/2025/legislation/SR107/", "note": ""}], "extras": {}, "jurisdiction": {"id": "ocd-jurisdiction/country:us/state:id/government", "name": "Idaho", "classification": "state", "division_id": "ocd-division/country:us/state:id"}, "scraped_at": "2025-07-25T05:30:54+00:00", "_id": "88a0813c-6918-11f0-b0ae-5a534b2ff75f"}