{
  "action": {
    "description": "Read third time in full \u2013 PASSED - 30-4-1AYES \u2013 Adams, Anthon, Bernt, Bjerke, Blaylock, Burtenshaw, Carlson, Cook, Den Hartog, Foreman, Galloway, Grow, Guthrie, Harris, Hart, Keyser, Kohl, Lakey, Lenney, Lent, Nichols, Okuniewicz, Ricks, Ruchti, Shippy, Toews, Ward-Engelking, Woodward, Zito, ZuiderveldNAYS \u2013 Bearg(Rabe), Semmelroth, Taylor, WintrowAbsent and excused \u2013 VanOrdenFloor Sponsor - ShippyTitle apvd - to House",
    "date": "2025-03-18",
    "organization_id": "~{\"classification\": \"upper\"}",
    "classification": [
      "passage"
    ],
    "related_entities": []
  },
  "bill_id": "H 0047"
}