{
  "legislative_session": "2025",
  "identifier": "S 1124",
  "title": "PUBLIC UTILITY REGULATION \u2013 Adds to existing law to provide for electric corporations\u2019 standard of care for wildfire liability.",
  "from_organization": "~{\"classification\": \"upper\"}",
  "classification": [
    "bill"
  ],
  "subject": [
    "ACTS",
    "ELECTRICITY AND ELECTRICIANS",
    "EMERGENCIES",
    "FIRE AND FIREFIGHTERS",
    "FORESTS AND FORESTRY",
    "INFRASTRUCTURE",
    "NATURAL RESOURCES",
    "UTILITIES",
    "WILDERNESS"
  ],
  "abstracts": [],
  "other_titles": [
    {
      "note": "short title",
      "title": "Wildfires, electric utilities"
    }
  ],
  "other_identifiers": [],
  "actions": [
    {
      "description": "Introduced; read first time; referred to JR for Printing",
      "date": "2025-02-21",
      "organization_id": "~{\"classification\": \"upper\"}",
      "classification": [
        "introduction"
      ],
      "related_entities": []
    },
    {
      "description": "Reported Printed; referred to State Affairs",
      "date": "2025-02-24",
      "organization_id": "~{\"classification\": \"upper\"}",
      "classification": [],
      "related_entities": []
    },
    {
      "description": "Reported out of committee; to 14th Order for amendment",
      "date": "2025-03-05",
      "organization_id": "~{\"classification\": \"upper\"}",
      "classification": [],
      "related_entities": []
    },
    {
      "description": "Placed in the Committee of the Whole",
      "date": "2025-03-07",
      "organization_id": "~{\"classification\": \"upper\"}",
      "classification": [],
      "related_entities": []
    },
    {
      "description": "Reported out without recommendation, as amended",
      "date": "2025-03-07",
      "organization_id": "~{\"classification\": \"upper\"}",
      "classification": [],
      "related_entities": []
    },
    {
      "description": "Amendments ordered printed; referred for engrossment",
      "date": "2025-03-07",
      "organization_id": "~{\"classification\": \"upper\"}",
      "classification": [],
      "related_entities": []
    },
    {
      "description": "Amendments reported printed",
      "date": "2025-03-07",
      "organization_id": "~{\"classification\": \"upper\"}",
      "classification": [],
      "related_entities": []
    },
    {
      "description": "Reported engrossed, filed for first reading, as amended",
      "date": "2025-03-07",
      "organization_id": "~{\"classification\": \"upper\"}",
      "classification": [],
      "related_entities": []
    },
    {
      "description": "Read first time as amended, filed for Second Reading",
      "date": "2025-03-07",
      "organization_id": "~{\"classification\": \"upper\"}",
      "classification": [],
      "related_entities": []
    },
    {
      "description": "Read second time as amended, filed for Third reading",
      "date": "2025-03-10",
      "organization_id": "~{\"classification\": \"upper\"}",
      "classification": [
        "reading-2"
      ],
      "related_entities": []
    },
    {
      "description": "Retained on calendar",
      "date": "2025-03-11",
      "organization_id": "~{\"classification\": \"upper\"}",
      "classification": [],
      "related_entities": []
    },
    {
      "description": "Read third time in full as amended \u2013 FAILED - 16-19-0AYES \u2013 Adams, Anthon, Bjerke, Blaylock, Burtenshaw, Cook, Den Hartog, Harris, Keyser, Lakey, Lent, Markley(Carlson), Okuniewicz, Toews, VanOrden, WoodwardNAYS \u2013 Bernt, Foreman, Galloway, Goodrich(Rabe), Grow, Guthrie, Hart, Kohl, Lenney, Nichols, Ricks, Ruchti, Semmelroth, Shippy, Taylor, Ward-Engelking, Wintrow, Zito, ZuiderveldAbsent and excused \u2013 NoneFloor Sponsor - WoodwardFiled in Office of the Secretary of Senate",
      "date": "2025-03-11",
      "organization_id": "~{\"classification\": \"upper\"}",
      "classification": [],
      "related_entities": []
    },
    {
      "description": "Notice to reconsider - Held at Desk",
      "date": "2025-03-11",
      "organization_id": "~{\"classification\": \"upper\"}",
      "classification": [],
      "related_entities": []
    },
    {
      "description": "UC to reconsider",
      "date": "2025-03-12",
      "organization_id": "~{\"classification\": \"upper\"}",
      "classification": [],
      "related_entities": []
    },
    {
      "description": "Motion to reconsider - PASSED",
      "date": "2025-03-12",
      "organization_id": "~{\"classification\": \"upper\"}",
      "classification": [],
      "related_entities": []
    },
    {
      "description": "Referred to 14th Order for amendment",
      "date": "2025-03-12",
      "organization_id": "~{\"classification\": \"upper\"}",
      "classification": [],
      "related_entities": []
    },
    {
      "description": "Recommitted to State Affairs",
      "date": "2025-03-27",
      "organization_id": "~{\"classification\": \"upper\"}",
      "classification": [],
      "related_entities": []
    }
  ],
  "sponsorships": [
    {
      "name": "STATE AFFAIRS COMMITTEE",
      "classification": "primary",
      "entity_type": "organization",
      "primary": true,
      "person_id": null,
      "organization_id": "~{\"chamber\": \"upper\", \"name\": \"STATE AFFAIRS COMMITTEE\"}"
    }
  ],
  "related_bills": [],
  "versions": [
    {
      "note": "Bill Text",
      "links": [
        {
          "url": "https://legislature.idaho.gov/wp-content/uploads/sessioninfo/2025/legislation/S1124.pdf",
          "media_type": "application/pdf"
        }
      ],
      "date": "",
      "classification": ""
    },
    {
      "note": "Amendment",
      "links": [
        {
          "url": "https://legislature.idaho.gov/wp-content/uploads/sessioninfo/2025/legislation/S1124A1.pdf",
          "media_type": "application/pdf"
        }
      ],
      "date": "",
      "classification": ""
    },
    {
      "note": "Engrossment 1",
      "links": [
        {
          "url": "https://legislature.idaho.gov/wp-content/uploads/sessioninfo/2025/legislation/S1124E1.pdf",
          "media_type": "application/pdf"
        }
      ],
      "date": "",
      "classification": ""
    }
  ],
  "documents": [
    {
      "note": "Statement of Purpose / Fiscal Note",
      "links": [
        {
          "url": "https://legislature.idaho.gov/wp-content/uploads/sessioninfo/2025/legislation/S1124SOP.pdf",
          "media_type": "application/pdf"
        }
      ],
      "date": "",
      "classification": ""
    },
    {
      "note": "Legislative Co-sponsors",
      "links": [
        {
          "url": "https://legislature.idaho.gov/wp-content/uploads/sessioninfo/2025/legislation/S1124LegCo.pdf",
          "media_type": "application/pdf"
        }
      ],
      "date": "",
      "classification": ""
    }
  ],
  "citations": [],
  "sources": [
    {
      "url": "https://legislature.idaho.gov/sessioninfo/2025/legislation/S1124/",
      "note": ""
    }
  ],
  "extras": {},
  "jurisdiction": {
    "id": "ocd-jurisdiction/country:us/state:id/government",
    "name": "Idaho",
    "classification": "state",
    "division_id": "ocd-division/country:us/state:id"
  },
  "scraped_at": "2025-07-25T05:38:33+00:00",
  "_id": "9aaedb20-6919-11f0-bb76-6acb18b786c2"
}