{
  "action": {
    "description": "Read third time in full \u2013 PASSED - 32-0-3AYES \u2013 Anthon, Bernt, Bjerke, Blaylock, Burtenshaw, Carlson, Cook, Den Hartog, Foreman, Goodrich(Rabe), Grow, Guthrie, Harris, Hart, Keyser, Kohl, Lakey, Lenney, Lent, Nichols, Okuniewicz, Ricks, Ruchti, Semmelroth, Shippy, Taylor, Toews, VanOrden, Wintrow, Woodward, Zito, ZuiderveldNAYS \u2013 NoneAbsent and excused \u2013 Adams, Galloway, Ward-EngelkingFloor Sponsor - BerntTitle apvd - to House",
    "date": "2025-03-13",
    "organization_id": "~{\"classification\": \"upper\"}",
    "classification": [
      "passage"
    ],
    "related_entities": []
  },
  "bill_id": "H 0227"
}